{
	"configurations" : 
	[
		{
			"directories" : 
			[
				{
					"build" : ".",
					"hasInstallRule" : true,
					"jsonFile" : "directory-.-5c976a75d85ed3e6ff07.json",
					"minimumCMakeVersion" : 
					{
						"string" : "3.12"
					},
					"projectIndex" : 0,
					"source" : ".",
					"targetIndexes" : 
					[
						0,
						1,
						2,
						3
					]
				}
			],
			"name" : "",
			"projects" : 
			[
				{
					"directoryIndexes" : 
					[
						0
					],
					"name" : "mapping_pkg",
					"targetIndexes" : 
					[
						0,
						1,
						2,
						3
					]
				}
			],
			"targets" : 
			[
				{
					"directoryIndex" : 0,
					"id" : "ament_cmake_python_build_mapping_pkg_egg::@6890427a1f51a3e7e1df",
					"jsonFile" : "target-ament_cmake_python_build_mapping_pkg_egg-53569b6d1c14c69e4a88.json",
					"name" : "ament_cmake_python_build_mapping_pkg_egg",
					"projectIndex" : 0
				},
				{
					"directoryIndex" : 0,
					"id" : "ament_cmake_python_copy_mapping_pkg::@6890427a1f51a3e7e1df",
					"jsonFile" : "target-ament_cmake_python_copy_mapping_pkg-ca303089f44339b5cd89.json",
					"name" : "ament_cmake_python_copy_mapping_pkg",
					"projectIndex" : 0
				},
				{
					"directoryIndex" : 0,
					"id" : "mapping_pkg_uninstall::@6890427a1f51a3e7e1df",
					"jsonFile" : "target-mapping_pkg_uninstall-829b628d6fe706dfe071.json",
					"name" : "mapping_pkg_uninstall",
					"projectIndex" : 0
				},
				{
					"directoryIndex" : 0,
					"id" : "uninstall::@6890427a1f51a3e7e1df",
					"jsonFile" : "target-uninstall-a2f72801b377fa9794b6.json",
					"name" : "uninstall",
					"projectIndex" : 0
				}
			]
		}
	],
	"kind" : "codemodel",
	"paths" : 
	{
		"build" : "/home/shiva16/ros2_playground/patrol_bot/build/mapping_pkg",
		"source" : "/home/shiva16/ros2_playground/patrol_bot/src/mapping_pkg"
	},
	"version" : 
	{
		"major" : 2,
		"minor" : 3
	}
}
